[
    {
        "player": "William Carrier",
        "team": "CAR",
        "opponent": "MTL",
        "hit_rate": 100,
        "last_10": 10
    },
    {
        "player": "Nicolas Deslauriers",
        "team": "CAR",
        "opponent": "MTL",
        "hit_rate": 100,
        "last_10": 10
    },
    {
        "player": "Jesperi Kotkaniemi",
        "team": "CAR",
        "opponent": "MTL",
        "hit_rate": 100,
        "last_10": 10
    },
    {
        "player": "Eric Robinson",
        "team": "CAR",
        "opponent": "MTL",
        "hit_rate": 100,
        "last_10": 10
    },
    {
        "player": "K'Andre Miller",
        "team": "CAR",
        "opponent": "MTL",
        "hit_rate": 100,
        "last_10": 10
    },
    {
        "player": "Alexander Nikishin",
        "team": "CAR",
        "opponent": "MTL",
        "hit_rate": 100,
        "last_10": 10
    },
    {
        "player": "Jaccob Slavin",
        "team": "CAR",
        "opponent": "MTL",
        "hit_rate": 100,
        "last_10": 10
    },
    {
        "player": "Sean Walker",
        "team": "CAR",
        "opponent": "MTL",
        "hit_rate": 100,
        "last_10": 10
    },
    {
        "player": "Owen Beck",
        "team": "MTL",
        "opponent": "CAR",
        "hit_rate": 100,
        "last_10": 10
    },
    {
        "player": "Zachary Bolduc",
        "team": "MTL",
        "opponent": "CAR",
        "hit_rate": 100,
        "last_10": 10
    },
    {
        "player": "Kirby Dach",
        "team": "MTL",
        "opponent": "CAR",
        "hit_rate": 100,
        "last_10": 10
    },
    {
        "player": "Brendan Gallagher",
        "team": "MTL",
        "opponent": "CAR",
        "hit_rate": 100,
        "last_10": 10
    },
    {
        "player": "Oliver Kapanen",
        "team": "MTL",
        "opponent": "CAR",
        "hit_rate": 100,
        "last_10": 10
    },
    {
        "player": "Alexandre Texier",
        "team": "MTL",
        "opponent": "CAR",
        "hit_rate": 100,
        "last_10": 10
    },
    {
        "player": "Joe Veleno",
        "team": "MTL",
        "opponent": "CAR",
        "hit_rate": 100,
        "last_10": 10
    },
    {
        "player": "Alexandre Carrier",
        "team": "MTL",
        "opponent": "CAR",
        "hit_rate": 100,
        "last_10": 10
    },
    {
        "player": "Noah Dobson",
        "team": "MTL",
        "opponent": "CAR",
        "hit_rate": 100,
        "last_10": 10
    },
    {
        "player": "Adam Engstrom",
        "team": "MTL",
        "opponent": "CAR",
        "hit_rate": 100,
        "last_10": 10
    },
    {
        "player": "Mike Matheson",
        "team": "MTL",
        "opponent": "CAR",
        "hit_rate": 100,
        "last_10": 10
    },
    {
        "player": "Jayden Struble",
        "team": "MTL",
        "opponent": "CAR",
        "hit_rate": 100,
        "last_10": 10
    },
    {
        "player": "Arber Xhekaj",
        "team": "MTL",
        "opponent": "CAR",
        "hit_rate": 100,
        "last_10": 10
    },
    {
        "player": "Sebastian Aho",
        "team": "CAR",
        "opponent": "MTL",
        "hit_rate": 90,
        "last_10": 9
    },
    {
        "player": "Mark Jankowski",
        "team": "CAR",
        "opponent": "MTL",
        "hit_rate": 90,
        "last_10": 9
    },
    {
        "player": "Seth Jarvis",
        "team": "CAR",
        "opponent": "MTL",
        "hit_rate": 90,
        "last_10": 9
    },
    {
        "player": "Jordan Martinook",
        "team": "CAR",
        "opponent": "MTL",
        "hit_rate": 90,
        "last_10": 9
    },
    {
        "player": "Jordan Staal",
        "team": "CAR",
        "opponent": "MTL",
        "hit_rate": 90,
        "last_10": 9
    },
    {
        "player": "Andrei Svechnikov",
        "team": "CAR",
        "opponent": "MTL",
        "hit_rate": 90,
        "last_10": 9
    },
    {
        "player": "Jalen Chatfield",
        "team": "CAR",
        "opponent": "MTL",
        "hit_rate": 90,
        "last_10": 9
    },
    {
        "player": "Shayne Gostisbehere",
        "team": "CAR",
        "opponent": "MTL",
        "hit_rate": 90,
        "last_10": 9
    },
    {
        "player": "Charles Alexis Legault",
        "team": "CAR",
        "opponent": "MTL",
        "hit_rate": 90,
        "last_10": 9
    },
    {
        "player": "Mike Reilly",
        "team": "CAR",
        "opponent": "MTL",
        "hit_rate": 90,
        "last_10": 9
    },
    {
        "player": "Josh Anderson",
        "team": "MTL",
        "opponent": "CAR",
        "hit_rate": 90,
        "last_10": 9
    },
    {
        "player": "Ivan Demidov",
        "team": "MTL",
        "opponent": "CAR",
        "hit_rate": 90,
        "last_10": 9
    },
    {
        "player": "Kaiden Guhle",
        "team": "MTL",
        "opponent": "CAR",
        "hit_rate": 90,
        "last_10": 9
    },
    {
        "player": "Nikolaj Ehlers",
        "team": "CAR",
        "opponent": "MTL",
        "hit_rate": 80,
        "last_10": 8
    },
    {
        "player": "Logan Stankoven",
        "team": "CAR",
        "opponent": "MTL",
        "hit_rate": 80,
        "last_10": 8
    },
    {
        "player": "Cole Caufield",
        "team": "MTL",
        "opponent": "CAR",
        "hit_rate": 80,
        "last_10": 8
    },
    {
        "player": "Jake Evans",
        "team": "MTL",
        "opponent": "CAR",
        "hit_rate": 80,
        "last_10": 8
    },
    {
        "player": "Alex Newhook",
        "team": "MTL",
        "opponent": "CAR",
        "hit_rate": 80,
        "last_10": 8
    },
    {
        "player": "Juraj Slafkovsk\u00fd",
        "team": "MTL",
        "opponent": "CAR",
        "hit_rate": 80,
        "last_10": 8
    },
    {
        "player": "Nick Suzuki",
        "team": "MTL",
        "opponent": "CAR",
        "hit_rate": 80,
        "last_10": 8
    },
    {
        "player": "Lane Hutson",
        "team": "MTL",
        "opponent": "CAR",
        "hit_rate": 80,
        "last_10": 8
    }
]