[
    {
        "player": "Conor Geekie",
        "team": "TBL",
        "opponent": "MTL",
        "hit_rate": 100,
        "last_10": 10
    },
    {
        "player": "Zemgus Girgensons",
        "team": "TBL",
        "opponent": "MTL",
        "hit_rate": 100,
        "last_10": 10
    },
    {
        "player": "Scott Sabourin",
        "team": "TBL",
        "opponent": "MTL",
        "hit_rate": 100,
        "last_10": 10
    },
    {
        "player": "Alexandre Carrier",
        "team": "MTL",
        "opponent": "TBL",
        "hit_rate": 100,
        "last_10": 10
    },
    {
        "player": "Keegan Kolesar",
        "team": "VGK",
        "opponent": "UTA",
        "hit_rate": 100,
        "last_10": 10
    },
    {
        "player": "Kaedan Korczak",
        "team": "VGK",
        "opponent": "UTA",
        "hit_rate": 100,
        "last_10": 10
    },
    {
        "player": "Ian Cole",
        "team": "UTA",
        "opponent": "VGK",
        "hit_rate": 100,
        "last_10": 10
    },
    {
        "player": "Mattias Janmark",
        "team": "EDM",
        "opponent": "ANA",
        "hit_rate": 100,
        "last_10": 10
    },
    {
        "player": "Curtis Lazar",
        "team": "EDM",
        "opponent": "ANA",
        "hit_rate": 100,
        "last_10": 10
    },
    {
        "player": "Spencer Stastney",
        "team": "EDM",
        "opponent": "ANA",
        "hit_rate": 100,
        "last_10": 10
    },
    {
        "player": "Tim Washe",
        "team": "ANA",
        "opponent": "EDM",
        "hit_rate": 100,
        "last_10": 10
    },
    {
        "player": "Erik Cernak",
        "team": "TBL",
        "opponent": "MTL",
        "hit_rate": 90,
        "last_10": 9
    },
    {
        "player": "Emil Lilleberg",
        "team": "TBL",
        "opponent": "MTL",
        "hit_rate": 90,
        "last_10": 9
    },
    {
        "player": "Ryan McDonagh",
        "team": "TBL",
        "opponent": "MTL",
        "hit_rate": 90,
        "last_10": 9
    },
    {
        "player": "Joe Veleno",
        "team": "MTL",
        "opponent": "TBL",
        "hit_rate": 90,
        "last_10": 9
    },
    {
        "player": "Jayden Struble",
        "team": "MTL",
        "opponent": "TBL",
        "hit_rate": 90,
        "last_10": 9
    },
    {
        "player": "Arber Xhekaj",
        "team": "MTL",
        "opponent": "TBL",
        "hit_rate": 90,
        "last_10": 9
    },
    {
        "player": "Alexander Kerfoot",
        "team": "UTA",
        "opponent": "VGK",
        "hit_rate": 90,
        "last_10": 9
    },
    {
        "player": "Nick DeSimone",
        "team": "UTA",
        "opponent": "VGK",
        "hit_rate": 90,
        "last_10": 9
    },
    {
        "player": "Mattias Ekholm",
        "team": "EDM",
        "opponent": "ANA",
        "hit_rate": 90,
        "last_10": 9
    },
    {
        "player": "Ty Emberson",
        "team": "EDM",
        "opponent": "ANA",
        "hit_rate": 90,
        "last_10": 9
    },
    {
        "player": "Ross Johnston",
        "team": "ANA",
        "opponent": "EDM",
        "hit_rate": 90,
        "last_10": 9
    },
    {
        "player": "Drew Helleson",
        "team": "ANA",
        "opponent": "EDM",
        "hit_rate": 90,
        "last_10": 9
    },
    {
        "player": "Olen Zellweger",
        "team": "ANA",
        "opponent": "EDM",
        "hit_rate": 90,
        "last_10": 9
    },
    {
        "player": "Gage Goncalves",
        "team": "TBL",
        "opponent": "MTL",
        "hit_rate": 80,
        "last_10": 8
    },
    {
        "player": "Declan Carlile",
        "team": "TBL",
        "opponent": "MTL",
        "hit_rate": 80,
        "last_10": 8
    },
    {
        "player": "Zachary Bolduc",
        "team": "MTL",
        "opponent": "TBL",
        "hit_rate": 80,
        "last_10": 8
    },
    {
        "player": "Kirby Dach",
        "team": "MTL",
        "opponent": "TBL",
        "hit_rate": 80,
        "last_10": 8
    },
    {
        "player": "Oliver Kapanen",
        "team": "MTL",
        "opponent": "TBL",
        "hit_rate": 80,
        "last_10": 8
    },
    {
        "player": "Adam Engstrom",
        "team": "MTL",
        "opponent": "TBL",
        "hit_rate": 80,
        "last_10": 8
    },
    {
        "player": "Cole Smith",
        "team": "VGK",
        "opponent": "UTA",
        "hit_rate": 80,
        "last_10": 8
    },
    {
        "player": "Kevin Stenlund",
        "team": "UTA",
        "opponent": "VGK",
        "hit_rate": 80,
        "last_10": 8
    },
    {
        "player": "Brandon Tanev",
        "team": "UTA",
        "opponent": "VGK",
        "hit_rate": 80,
        "last_10": 8
    },
    {
        "player": "John Marino",
        "team": "UTA",
        "opponent": "VGK",
        "hit_rate": 80,
        "last_10": 8
    },
    {
        "player": "Nate Schmidt",
        "team": "UTA",
        "opponent": "VGK",
        "hit_rate": 80,
        "last_10": 8
    },
    {
        "player": "Dmitri Simashev",
        "team": "UTA",
        "opponent": "VGK",
        "hit_rate": 80,
        "last_10": 8
    },
    {
        "player": "Colton Dach",
        "team": "EDM",
        "opponent": "ANA",
        "hit_rate": 80,
        "last_10": 8
    },
    {
        "player": "Max Jones",
        "team": "EDM",
        "opponent": "ANA",
        "hit_rate": 80,
        "last_10": 8
    },
    {
        "player": "Josh Samanski",
        "team": "EDM",
        "opponent": "ANA",
        "hit_rate": 80,
        "last_10": 8
    },
    {
        "player": "Frank Vatrano",
        "team": "ANA",
        "opponent": "EDM",
        "hit_rate": 80,
        "last_10": 8
    }
]