[
    {
        "player": "Tyson Kozak",
        "team": "BUF",
        "opponent": "OTT",
        "hit_rate": 100,
        "last_10": 10
    },
    {
        "player": "Kurtis MacDermid",
        "team": "OTT",
        "opponent": "BUF",
        "hit_rate": 100,
        "last_10": 10
    },
    {
        "player": "Nick Jensen",
        "team": "OTT",
        "opponent": "BUF",
        "hit_rate": 100,
        "last_10": 10
    },
    {
        "player": "Samuel Girard",
        "team": "PIT",
        "opponent": "TBL",
        "hit_rate": 100,
        "last_10": 10
    },
    {
        "player": "Ryan Shea",
        "team": "PIT",
        "opponent": "TBL",
        "hit_rate": 100,
        "last_10": 10
    },
    {
        "player": "Scott Sabourin",
        "team": "TBL",
        "opponent": "PIT",
        "hit_rate": 100,
        "last_10": 10
    },
    {
        "player": "Phillip Danault",
        "team": "MTL",
        "opponent": "NYR",
        "hit_rate": 100,
        "last_10": 10
    },
    {
        "player": "Alexandre Carrier",
        "team": "MTL",
        "opponent": "NYR",
        "hit_rate": 100,
        "last_10": 10
    },
    {
        "player": "Jacob Bernard-Docker",
        "team": "DET",
        "opponent": "PHI",
        "hit_rate": 100,
        "last_10": 10
    },
    {
        "player": "Jake Christiansen",
        "team": "CBJ",
        "opponent": "CAR",
        "hit_rate": 100,
        "last_10": 10
    },
    {
        "player": "Dante Fabbro",
        "team": "CBJ",
        "opponent": "CAR",
        "hit_rate": 100,
        "last_10": 10
    },
    {
        "player": "Hendrix Lapierre",
        "team": "WSH",
        "opponent": "NJD",
        "hit_rate": 100,
        "last_10": 10
    },
    {
        "player": "Martin Feh\u00e9rv\u00e1ry",
        "team": "WSH",
        "opponent": "NJD",
        "hit_rate": 100,
        "last_10": 10
    },
    {
        "player": "Nick Bjugstad",
        "team": "NJD",
        "opponent": "WSH",
        "hit_rate": 100,
        "last_10": 10
    },
    {
        "player": "Parker Ford",
        "team": "WPG",
        "opponent": "DAL",
        "hit_rate": 100,
        "last_10": 10
    },
    {
        "player": "Radek Faksa",
        "team": "DAL",
        "opponent": "WPG",
        "hit_rate": 100,
        "last_10": 10
    },
    {
        "player": "Kyle Capobianco",
        "team": "DAL",
        "opponent": "WPG",
        "hit_rate": 100,
        "last_10": 10
    },
    {
        "player": "Marcus Pettersson",
        "team": "VAN",
        "opponent": "MIN",
        "hit_rate": 100,
        "last_10": 10
    },
    {
        "player": "Nico Sturm",
        "team": "MIN",
        "opponent": "VAN",
        "hit_rate": 100,
        "last_10": 10
    },
    {
        "player": "Sam Lafferty",
        "team": "CHI",
        "opponent": "EDM",
        "hit_rate": 100,
        "last_10": 10
    },
    {
        "player": "Mattias Janmark",
        "team": "EDM",
        "opponent": "CHI",
        "hit_rate": 100,
        "last_10": 10
    },
    {
        "player": "Curtis Lazar",
        "team": "EDM",
        "opponent": "CHI",
        "hit_rate": 100,
        "last_10": 10
    },
    {
        "player": "Josh Samanski",
        "team": "EDM",
        "opponent": "CHI",
        "hit_rate": 100,
        "last_10": 10
    },
    {
        "player": "Spencer Stastney",
        "team": "EDM",
        "opponent": "CHI",
        "hit_rate": 100,
        "last_10": 10
    },
    {
        "player": "Ryan Reaves",
        "team": "SJS",
        "opponent": "TOR",
        "hit_rate": 100,
        "last_10": 10
    },
    {
        "player": "Brandon Tanev",
        "team": "UTA",
        "opponent": "SEA",
        "hit_rate": 100,
        "last_10": 10
    },
    {
        "player": "John Marino",
        "team": "UTA",
        "opponent": "SEA",
        "hit_rate": 100,
        "last_10": 10
    },
    {
        "player": "Ryker Evans",
        "team": "SEA",
        "opponent": "UTA",
        "hit_rate": 100,
        "last_10": 10
    },
    {
        "player": "Cale Fleury",
        "team": "SEA",
        "opponent": "UTA",
        "hit_rate": 100,
        "last_10": 10
    },
    {
        "player": "Ozzy Wiesblatt",
        "team": "NSH",
        "opponent": "LAK",
        "hit_rate": 100,
        "last_10": 10
    },
    {
        "player": "Ryan Ufko",
        "team": "NSH",
        "opponent": "LAK",
        "hit_rate": 100,
        "last_10": 10
    },
    {
        "player": "Cody Ceci",
        "team": "LAK",
        "opponent": "NSH",
        "hit_rate": 100,
        "last_10": 10
    },
    {
        "player": "Brian Dumoulin",
        "team": "LAK",
        "opponent": "NSH",
        "hit_rate": 100,
        "last_10": 10
    },
    {
        "player": "Jordan Greenway",
        "team": "BUF",
        "opponent": "OTT",
        "hit_rate": 90,
        "last_10": 9
    },
    {
        "player": "Zach Metsa",
        "team": "BUF",
        "opponent": "OTT",
        "hit_rate": 90,
        "last_10": 9
    },
    {
        "player": "Mattias Samuelsson",
        "team": "BUF",
        "opponent": "OTT",
        "hit_rate": 90,
        "last_10": 9
    },
    {
        "player": "Luke Schenn",
        "team": "BUF",
        "opponent": "OTT",
        "hit_rate": 90,
        "last_10": 9
    },
    {
        "player": "Ville Koivunen",
        "team": "PIT",
        "opponent": "TBL",
        "hit_rate": 90,
        "last_10": 9
    },
    {
        "player": "Declan Carlile",
        "team": "TBL",
        "opponent": "PIT",
        "hit_rate": 90,
        "last_10": 9
    },
    {
        "player": "Erik Cernak",
        "team": "TBL",
        "opponent": "PIT",
        "hit_rate": 90,
        "last_10": 9
    },
    {
        "player": "Ryan McDonagh",
        "team": "TBL",
        "opponent": "PIT",
        "hit_rate": 90,
        "last_10": 9
    },
    {
        "player": "Steven Santini",
        "team": "TBL",
        "opponent": "PIT",
        "hit_rate": 90,
        "last_10": 9
    },
    {
        "player": "Lukas Reichel",
        "team": "BOS",
        "opponent": "FLA",
        "hit_rate": 90,
        "last_10": 9
    },
    {
        "player": "Jesper Boqvist",
        "team": "FLA",
        "opponent": "BOS",
        "hit_rate": 90,
        "last_10": 9
    },
    {
        "player": "Cole Reinhardt",
        "team": "FLA",
        "opponent": "BOS",
        "hit_rate": 90,
        "last_10": 9
    },
    {
        "player": "Mike Benning",
        "team": "FLA",
        "opponent": "BOS",
        "hit_rate": 90,
        "last_10": 9
    },
    {
        "player": "Dmitry Kulikov",
        "team": "FLA",
        "opponent": "BOS",
        "hit_rate": 90,
        "last_10": 9
    },
    {
        "player": "Donovan Sebrango",
        "team": "FLA",
        "opponent": "BOS",
        "hit_rate": 90,
        "last_10": 9
    },
    {
        "player": "Joe Veleno",
        "team": "MTL",
        "opponent": "NYR",
        "hit_rate": 90,
        "last_10": 9
    },
    {
        "player": "Arber Xhekaj",
        "team": "MTL",
        "opponent": "NYR",
        "hit_rate": 90,
        "last_10": 9
    },
    {
        "player": "Matt Rempe",
        "team": "NYR",
        "opponent": "MTL",
        "hit_rate": 90,
        "last_10": 9
    },
    {
        "player": "Braden Schneider",
        "team": "NYR",
        "opponent": "MTL",
        "hit_rate": 90,
        "last_10": 9
    },
    {
        "player": "Michael Rasmussen",
        "team": "DET",
        "opponent": "PHI",
        "hit_rate": 90,
        "last_10": 9
    },
    {
        "player": "Dominik Shine",
        "team": "DET",
        "opponent": "PHI",
        "hit_rate": 90,
        "last_10": 9
    },
    {
        "player": "Travis Hamonic",
        "team": "DET",
        "opponent": "PHI",
        "hit_rate": 90,
        "last_10": 9
    },
    {
        "player": "Nikita Grebenkin",
        "team": "PHI",
        "opponent": "DET",
        "hit_rate": 90,
        "last_10": 9
    },
    {
        "player": "Noah Juulsen",
        "team": "PHI",
        "opponent": "DET",
        "hit_rate": 90,
        "last_10": 9
    },
    {
        "player": "Zachary Aston-Reese",
        "team": "CBJ",
        "opponent": "CAR",
        "hit_rate": 90,
        "last_10": 9
    },
    {
        "player": "Danton Heinen",
        "team": "CBJ",
        "opponent": "CAR",
        "hit_rate": 90,
        "last_10": 9
    },
    {
        "player": "Egor Zamula",
        "team": "CBJ",
        "opponent": "CAR",
        "hit_rate": 90,
        "last_10": 9
    },
    {
        "player": "Pierre-Luc Dubois",
        "team": "WSH",
        "opponent": "NJD",
        "hit_rate": 90,
        "last_10": 9
    },
    {
        "player": "Ethen Frank",
        "team": "WSH",
        "opponent": "NJD",
        "hit_rate": 90,
        "last_10": 9
    },
    {
        "player": "Declan Chisholm",
        "team": "WSH",
        "opponent": "NJD",
        "hit_rate": 90,
        "last_10": 9
    },
    {
        "player": "Dylan McIlrath",
        "team": "WSH",
        "opponent": "NJD",
        "hit_rate": 90,
        "last_10": 9
    },
    {
        "player": "Paul Cotter",
        "team": "NJD",
        "opponent": "WSH",
        "hit_rate": 90,
        "last_10": 9
    },
    {
        "player": "Dennis Cholowski",
        "team": "NJD",
        "opponent": "WSH",
        "hit_rate": 90,
        "last_10": 9
    },
    {
        "player": "Isak Rosen",
        "team": "WPG",
        "opponent": "DAL",
        "hit_rate": 90,
        "last_10": 9
    },
    {
        "player": "Dylan DeMelo",
        "team": "WPG",
        "opponent": "DAL",
        "hit_rate": 90,
        "last_10": 9
    },
    {
        "player": "Haydn Fleury",
        "team": "WPG",
        "opponent": "DAL",
        "hit_rate": 90,
        "last_10": 9
    },
    {
        "player": "Elias Salomonsson",
        "team": "WPG",
        "opponent": "DAL",
        "hit_rate": 90,
        "last_10": 9
    },
    {
        "player": "Oskar B\u00e4ck",
        "team": "DAL",
        "opponent": "WPG",
        "hit_rate": 90,
        "last_10": 9
    },
    {
        "player": "Tyler Seguin",
        "team": "DAL",
        "opponent": "WPG",
        "hit_rate": 90,
        "last_10": 9
    },
    {
        "player": "Nils Hoglander",
        "team": "VAN",
        "opponent": "MIN",
        "hit_rate": 90,
        "last_10": 9
    },
    {
        "player": "Aatu R\u00e4ty",
        "team": "VAN",
        "opponent": "MIN",
        "hit_rate": 90,
        "last_10": 9
    },
    {
        "player": "Elias Pettersson",
        "team": "VAN",
        "opponent": "MIN",
        "hit_rate": 90,
        "last_10": 9
    },
    {
        "player": "Tom Willander",
        "team": "VAN",
        "opponent": "MIN",
        "hit_rate": 90,
        "last_10": 9
    },
    {
        "player": "Zach Bogosian",
        "team": "MIN",
        "opponent": "VAN",
        "hit_rate": 90,
        "last_10": 9
    },
    {
        "player": "Teuvo Teravainen",
        "team": "CHI",
        "opponent": "EDM",
        "hit_rate": 90,
        "last_10": 9
    },
    {
        "player": "Colton Dach",
        "team": "EDM",
        "opponent": "CHI",
        "hit_rate": 90,
        "last_10": 9
    },
    {
        "player": "Ty Emberson",
        "team": "EDM",
        "opponent": "CHI",
        "hit_rate": 90,
        "last_10": 9
    },
    {
        "player": "Brennan Othmann",
        "team": "CGY",
        "opponent": "VGK",
        "hit_rate": 90,
        "last_10": 9
    },
    {
        "player": "Kevin Bahl",
        "team": "CGY",
        "opponent": "VGK",
        "hit_rate": 90,
        "last_10": 9
    },
    {
        "player": "Brayden Pachal",
        "team": "CGY",
        "opponent": "VGK",
        "hit_rate": 90,
        "last_10": 9
    },
    {
        "player": "Brett Howden",
        "team": "VGK",
        "opponent": "CGY",
        "hit_rate": 90,
        "last_10": 9
    },
    {
        "player": "Keegan Kolesar",
        "team": "VGK",
        "opponent": "CGY",
        "hit_rate": 90,
        "last_10": 9
    },
    {
        "player": "Kaedan Korczak",
        "team": "VGK",
        "opponent": "CGY",
        "hit_rate": 90,
        "last_10": 9
    },
    {
        "player": "Jacob Quillan",
        "team": "TOR",
        "opponent": "SJS",
        "hit_rate": 90,
        "last_10": 9
    },
    {
        "player": "Chris Tanev",
        "team": "TOR",
        "opponent": "SJS",
        "hit_rate": 90,
        "last_10": 9
    },
    {
        "player": "Ty Dellandrea",
        "team": "SJS",
        "opponent": "TOR",
        "hit_rate": 90,
        "last_10": 9
    },
    {
        "player": "Barclay Goodrow",
        "team": "SJS",
        "opponent": "TOR",
        "hit_rate": 90,
        "last_10": 9
    },
    {
        "player": "Liam O'Brien",
        "team": "UTA",
        "opponent": "SEA",
        "hit_rate": 90,
        "last_10": 9
    },
    {
        "player": "Nick DeSimone",
        "team": "UTA",
        "opponent": "SEA",
        "hit_rate": 90,
        "last_10": 9
    },
    {
        "player": "Sean Durzi",
        "team": "UTA",
        "opponent": "SEA",
        "hit_rate": 90,
        "last_10": 9
    },
    {
        "player": "Jacob Melanson",
        "team": "SEA",
        "opponent": "UTA",
        "hit_rate": 90,
        "last_10": 9
    },
    {
        "player": "Ben Meyers",
        "team": "SEA",
        "opponent": "UTA",
        "hit_rate": 90,
        "last_10": 9
    },
    {
        "player": "Ryan Lindgren",
        "team": "SEA",
        "opponent": "UTA",
        "hit_rate": 90,
        "last_10": 9
    },
    {
        "player": "Joshua Mahura",
        "team": "SEA",
        "opponent": "UTA",
        "hit_rate": 90,
        "last_10": 9
    },
    {
        "player": "Reid Schaefer",
        "team": "NSH",
        "opponent": "LAK",
        "hit_rate": 90,
        "last_10": 9
    },
    {
        "player": "Fedor Svechkov",
        "team": "NSH",
        "opponent": "LAK",
        "hit_rate": 90,
        "last_10": 9
    },
    {
        "player": "Justin Barron",
        "team": "NSH",
        "opponent": "LAK",
        "hit_rate": 90,
        "last_10": 9
    },
    {
        "player": "Adam Wilsby",
        "team": "NSH",
        "opponent": "LAK",
        "hit_rate": 90,
        "last_10": 9
    },
    {
        "player": "Mathieu Joseph",
        "team": "LAK",
        "opponent": "NSH",
        "hit_rate": 90,
        "last_10": 9
    },
    {
        "player": "Jacob Moverare",
        "team": "LAK",
        "opponent": "NSH",
        "hit_rate": 90,
        "last_10": 9
    },
    {
        "player": "Josh Dunne",
        "team": "BUF",
        "opponent": "OTT",
        "hit_rate": 80,
        "last_10": 8
    },
    {
        "player": "Ryan McLeod",
        "team": "BUF",
        "opponent": "OTT",
        "hit_rate": 80,
        "last_10": 8
    },
    {
        "player": "Owen Power",
        "team": "BUF",
        "opponent": "OTT",
        "hit_rate": 80,
        "last_10": 8
    },
    {
        "player": "Logan Stanley",
        "team": "BUF",
        "opponent": "OTT",
        "hit_rate": 80,
        "last_10": 8
    },
    {
        "player": "Artem Zub",
        "team": "OTT",
        "opponent": "BUF",
        "hit_rate": 80,
        "last_10": 8
    },
    {
        "player": "Rutger McGroarty",
        "team": "PIT",
        "opponent": "TBL",
        "hit_rate": 80,
        "last_10": 8
    },
    {
        "player": "Elmer Soderblom",
        "team": "PIT",
        "opponent": "TBL",
        "hit_rate": 80,
        "last_10": 8
    },
    {
        "player": "Connor Clifton",
        "team": "PIT",
        "opponent": "TBL",
        "hit_rate": 80,
        "last_10": 8
    },
    {
        "player": "Kris Letang",
        "team": "PIT",
        "opponent": "TBL",
        "hit_rate": 80,
        "last_10": 8
    },
    {
        "player": "Ilya Solovyov",
        "team": "PIT",
        "opponent": "TBL",
        "hit_rate": 80,
        "last_10": 8
    },
    {
        "player": "Jack St. Ivany",
        "team": "PIT",
        "opponent": "TBL",
        "hit_rate": 80,
        "last_10": 8
    },
    {
        "player": "Nick Paul",
        "team": "TBL",
        "opponent": "PIT",
        "hit_rate": 80,
        "last_10": 8
    },
    {
        "player": "Corey Perry",
        "team": "TBL",
        "opponent": "PIT",
        "hit_rate": 80,
        "last_10": 8
    },
    {
        "player": "Charle-Edouard D'Astous",
        "team": "TBL",
        "opponent": "PIT",
        "hit_rate": 80,
        "last_10": 8
    },
    {
        "player": "J.J. Moser",
        "team": "TBL",
        "opponent": "PIT",
        "hit_rate": 80,
        "last_10": 8
    },
    {
        "player": "Alex Steeves",
        "team": "BOS",
        "opponent": "FLA",
        "hit_rate": 80,
        "last_10": 8
    },
    {
        "player": "Jonathan Aspirot",
        "team": "BOS",
        "opponent": "FLA",
        "hit_rate": 80,
        "last_10": 8
    },
    {
        "player": "Hampus Lindholm",
        "team": "BOS",
        "opponent": "FLA",
        "hit_rate": 80,
        "last_10": 8
    },
    {
        "player": "Jonah Gadjovich",
        "team": "FLA",
        "opponent": "BOS",
        "hit_rate": 80,
        "last_10": 8
    },
    {
        "player": "Luke Kunin",
        "team": "FLA",
        "opponent": "BOS",
        "hit_rate": 80,
        "last_10": 8
    },
    {
        "player": "Tomas Nosek",
        "team": "FLA",
        "opponent": "BOS",
        "hit_rate": 80,
        "last_10": 8
    },
    {
        "player": "Cole Schwindt",
        "team": "FLA",
        "opponent": "BOS",
        "hit_rate": 80,
        "last_10": 8
    },
    {
        "player": "Seth Jones",
        "team": "FLA",
        "opponent": "BOS",
        "hit_rate": 80,
        "last_10": 8
    },
    {
        "player": "Adam Engstrom",
        "team": "MTL",
        "opponent": "NYR",
        "hit_rate": 80,
        "last_10": 8
    },
    {
        "player": "Jayden Struble",
        "team": "MTL",
        "opponent": "NYR",
        "hit_rate": 80,
        "last_10": 8
    },
    {
        "player": "Noah Laba",
        "team": "NYR",
        "opponent": "MTL",
        "hit_rate": 80,
        "last_10": 8
    },
    {
        "player": "Taylor Raddysh",
        "team": "NYR",
        "opponent": "MTL",
        "hit_rate": 80,
        "last_10": 8
    },
    {
        "player": "Conor Sheary",
        "team": "NYR",
        "opponent": "MTL",
        "hit_rate": 80,
        "last_10": 8
    },
    {
        "player": "Will Borgen",
        "team": "NYR",
        "opponent": "MTL",
        "hit_rate": 80,
        "last_10": 8
    },
    {
        "player": "Vladislav Gavrikov",
        "team": "NYR",
        "opponent": "MTL",
        "hit_rate": 80,
        "last_10": 8
    },
    {
        "player": "Vincent Iorio",
        "team": "NYR",
        "opponent": "MTL",
        "hit_rate": 80,
        "last_10": 8
    },
    {
        "player": "Urho Vaakanainen",
        "team": "NYR",
        "opponent": "MTL",
        "hit_rate": 80,
        "last_10": 8
    },
    {
        "player": "Mason Appleton",
        "team": "DET",
        "opponent": "PHI",
        "hit_rate": 80,
        "last_10": 8
    },
    {
        "player": "Denver Barkey",
        "team": "PHI",
        "opponent": "DET",
        "hit_rate": 80,
        "last_10": 8
    },
    {
        "player": "Alex Bump",
        "team": "PHI",
        "opponent": "DET",
        "hit_rate": 80,
        "last_10": 8
    },
    {
        "player": "Carl Grundstrom",
        "team": "PHI",
        "opponent": "DET",
        "hit_rate": 80,
        "last_10": 8
    },
    {
        "player": "Emil Andrae",
        "team": "PHI",
        "opponent": "DET",
        "hit_rate": 80,
        "last_10": 8
    },
    {
        "player": "Rasmus Ristolainen",
        "team": "PHI",
        "opponent": "DET",
        "hit_rate": 80,
        "last_10": 8
    },
    {
        "player": "Luca Del Bel Belluz",
        "team": "CBJ",
        "opponent": "CAR",
        "hit_rate": 80,
        "last_10": 8
    },
    {
        "player": "Miles Wood",
        "team": "CBJ",
        "opponent": "CAR",
        "hit_rate": 80,
        "last_10": 8
    },
    {
        "player": "Denton Mateychuk",
        "team": "CBJ",
        "opponent": "CAR",
        "hit_rate": 80,
        "last_10": 8
    },
    {
        "player": "Brendan Smith",
        "team": "CBJ",
        "opponent": "CAR",
        "hit_rate": 80,
        "last_10": 8
    },
    {
        "player": "Nicolas Deslauriers",
        "team": "CAR",
        "opponent": "CBJ",
        "hit_rate": 80,
        "last_10": 8
    },
    {
        "player": "Mark Jankowski",
        "team": "CAR",
        "opponent": "CBJ",
        "hit_rate": 80,
        "last_10": 8
    },
    {
        "player": "Jesperi Kotkaniemi",
        "team": "CAR",
        "opponent": "CBJ",
        "hit_rate": 80,
        "last_10": 8
    },
    {
        "player": "Eric Robinson",
        "team": "CAR",
        "opponent": "CBJ",
        "hit_rate": 80,
        "last_10": 8
    },
    {
        "player": "Brandon Duhaime",
        "team": "WSH",
        "opponent": "NJD",
        "hit_rate": 80,
        "last_10": 8
    },
    {
        "player": "David Kampf",
        "team": "WSH",
        "opponent": "NJD",
        "hit_rate": 80,
        "last_10": 8
    },
    {
        "player": "Dylan Strome",
        "team": "WSH",
        "opponent": "NJD",
        "hit_rate": 80,
        "last_10": 8
    },
    {
        "player": "Evgenii Dadonov",
        "team": "NJD",
        "opponent": "WSH",
        "hit_rate": 80,
        "last_10": 8
    },
    {
        "player": "Brenden Dillon",
        "team": "NJD",
        "opponent": "WSH",
        "hit_rate": 80,
        "last_10": 8
    },
    {
        "player": "Johnathan Kovacevic",
        "team": "NJD",
        "opponent": "WSH",
        "hit_rate": 80,
        "last_10": 8
    },
    {
        "player": "Jonas Siegenthaler",
        "team": "NJD",
        "opponent": "WSH",
        "hit_rate": 80,
        "last_10": 8
    },
    {
        "player": "Adam Lowry",
        "team": "WPG",
        "opponent": "DAL",
        "hit_rate": 80,
        "last_10": 8
    },
    {
        "player": "Nino Niederreiter",
        "team": "WPG",
        "opponent": "DAL",
        "hit_rate": 80,
        "last_10": 8
    },
    {
        "player": "Jacob Bryson",
        "team": "WPG",
        "opponent": "DAL",
        "hit_rate": 80,
        "last_10": 8
    },
    {
        "player": "Nathan Bastian",
        "team": "DAL",
        "opponent": "WPG",
        "hit_rate": 80,
        "last_10": 8
    },
    {
        "player": "Jamie Benn",
        "team": "DAL",
        "opponent": "WPG",
        "hit_rate": 80,
        "last_10": 8
    },
    {
        "player": "Adam Erne",
        "team": "DAL",
        "opponent": "WPG",
        "hit_rate": 80,
        "last_10": 8
    },
    {
        "player": "Justin Hryckowian",
        "team": "DAL",
        "opponent": "WPG",
        "hit_rate": 80,
        "last_10": 8
    },
    {
        "player": "Arttu Hyry",
        "team": "DAL",
        "opponent": "WPG",
        "hit_rate": 80,
        "last_10": 8
    },
    {
        "player": "Sam Steel",
        "team": "DAL",
        "opponent": "WPG",
        "hit_rate": 80,
        "last_10": 8
    },
    {
        "player": "Esa Lindell",
        "team": "DAL",
        "opponent": "WPG",
        "hit_rate": 80,
        "last_10": 8
    },
    {
        "player": "Ilya Lyubushkin",
        "team": "DAL",
        "opponent": "WPG",
        "hit_rate": 80,
        "last_10": 8
    },
    {
        "player": "Tyler Myers",
        "team": "DAL",
        "opponent": "WPG",
        "hit_rate": 80,
        "last_10": 8
    },
    {
        "player": "Curtis Douglas",
        "team": "VAN",
        "opponent": "MIN",
        "hit_rate": 80,
        "last_10": 8
    },
    {
        "player": "Marco Rossi",
        "team": "VAN",
        "opponent": "MIN",
        "hit_rate": 80,
        "last_10": 8
    },
    {
        "player": "Zeev Buium",
        "team": "VAN",
        "opponent": "MIN",
        "hit_rate": 80,
        "last_10": 8
    },
    {
        "player": "Victor Mancini",
        "team": "VAN",
        "opponent": "MIN",
        "hit_rate": 80,
        "last_10": 8
    },
    {
        "player": "Michael McCarron",
        "team": "MIN",
        "opponent": "VAN",
        "hit_rate": 80,
        "last_10": 8
    },
    {
        "player": "Daemon Hunt",
        "team": "MIN",
        "opponent": "VAN",
        "hit_rate": 80,
        "last_10": 8
    },
    {
        "player": "Jake Middleton",
        "team": "MIN",
        "opponent": "VAN",
        "hit_rate": 80,
        "last_10": 8
    },
    {
        "player": "Jeff Petry",
        "team": "MIN",
        "opponent": "VAN",
        "hit_rate": 80,
        "last_10": 8
    },
    {
        "player": "Andrew Mangiapane",
        "team": "CHI",
        "opponent": "EDM",
        "hit_rate": 80,
        "last_10": 8
    },
    {
        "player": "Landon Slaggert",
        "team": "CHI",
        "opponent": "EDM",
        "hit_rate": 80,
        "last_10": 8
    },
    {
        "player": "Ethan Del Mastro",
        "team": "CHI",
        "opponent": "EDM",
        "hit_rate": 80,
        "last_10": 8
    },
    {
        "player": "Matt Grzelcyk",
        "team": "CHI",
        "opponent": "EDM",
        "hit_rate": 80,
        "last_10": 8
    },
    {
        "player": "Connor Murphy",
        "team": "EDM",
        "opponent": "CHI",
        "hit_rate": 80,
        "last_10": 8
    },
    {
        "player": "Samuel Honzek",
        "team": "CGY",
        "opponent": "VGK",
        "hit_rate": 80,
        "last_10": 8
    },
    {
        "player": "Martin Pospisil",
        "team": "CGY",
        "opponent": "VGK",
        "hit_rate": 80,
        "last_10": 8
    },
    {
        "player": "Zach Whitecloud",
        "team": "CGY",
        "opponent": "VGK",
        "hit_rate": 80,
        "last_10": 8
    },
    {
        "player": "Steven Lorentz",
        "team": "TOR",
        "opponent": "SJS",
        "hit_rate": 80,
        "last_10": 8
    },
    {
        "player": "Philippe Myers",
        "team": "TOR",
        "opponent": "SJS",
        "hit_rate": 80,
        "last_10": 8
    },
    {
        "player": "Troy Stecher",
        "team": "TOR",
        "opponent": "SJS",
        "hit_rate": 80,
        "last_10": 8
    },
    {
        "player": "Vincent Desharnais",
        "team": "SJS",
        "opponent": "TOR",
        "hit_rate": 80,
        "last_10": 8
    },
    {
        "player": "John Klingberg",
        "team": "SJS",
        "opponent": "TOR",
        "hit_rate": 80,
        "last_10": 8
    },
    {
        "player": "Nick Leddy",
        "team": "SJS",
        "opponent": "TOR",
        "hit_rate": 80,
        "last_10": 8
    },
    {
        "player": "Kevin Stenlund",
        "team": "UTA",
        "opponent": "SEA",
        "hit_rate": 80,
        "last_10": 8
    },
    {
        "player": "Kaapo Kakko",
        "team": "SEA",
        "opponent": "UTA",
        "hit_rate": 80,
        "last_10": 8
    },
    {
        "player": "Shane Wright",
        "team": "SEA",
        "opponent": "UTA",
        "hit_rate": 80,
        "last_10": 8
    },
    {
        "player": "Nick Perbix",
        "team": "NSH",
        "opponent": "LAK",
        "hit_rate": 80,
        "last_10": 8
    },
    {
        "player": "Samuel Helenius",
        "team": "LAK",
        "opponent": "NSH",
        "hit_rate": 80,
        "last_10": 8
    },
    {
        "player": "Jeff Malott",
        "team": "LAK",
        "opponent": "NSH",
        "hit_rate": 80,
        "last_10": 8
    },
    {
        "player": "Alex Turcotte",
        "team": "LAK",
        "opponent": "NSH",
        "hit_rate": 80,
        "last_10": 8
    },
    {
        "player": "Mikey Anderson",
        "team": "LAK",
        "opponent": "NSH",
        "hit_rate": 80,
        "last_10": 8
    },
    {
        "player": "Joel Edmundson",
        "team": "LAK",
        "opponent": "NSH",
        "hit_rate": 80,
        "last_10": 8
    }
]