[
    {
        "player": "Dylan Holloway",
        "team": "STL",
        "opponent": "UTA",
        "hit_rate": 100,
        "last_10": 10
    },
    {
        "player": "Macklin Celebrini",
        "team": "SJS",
        "opponent": "WPG",
        "hit_rate": 100,
        "last_10": 10
    },
    {
        "player": "Kyle Connor",
        "team": "WPG",
        "opponent": "SJS",
        "hit_rate": 100,
        "last_10": 10
    },
    {
        "player": "Alex Laferriere",
        "team": "LAK",
        "opponent": "CGY",
        "hit_rate": 100,
        "last_10": 10
    },
    {
        "player": "Bobby McMann",
        "team": "SEA",
        "opponent": "COL",
        "hit_rate": 100,
        "last_10": 10
    },
    {
        "player": "Jimmy Snuggerud",
        "team": "STL",
        "opponent": "UTA",
        "hit_rate": 90,
        "last_10": 9
    },
    {
        "player": "Clayton Keller",
        "team": "UTA",
        "opponent": "STL",
        "hit_rate": 90,
        "last_10": 9
    },
    {
        "player": "Cutter Gauthier",
        "team": "ANA",
        "opponent": "NSH",
        "hit_rate": 90,
        "last_10": 9
    },
    {
        "player": "Troy Terry",
        "team": "ANA",
        "opponent": "NSH",
        "hit_rate": 90,
        "last_10": 9
    },
    {
        "player": "Jacob Trouba",
        "team": "ANA",
        "opponent": "NSH",
        "hit_rate": 90,
        "last_10": 9
    },
    {
        "player": "Roman Josi",
        "team": "NSH",
        "opponent": "ANA",
        "hit_rate": 90,
        "last_10": 9
    },
    {
        "player": "Blake Coleman",
        "team": "CGY",
        "opponent": "LAK",
        "hit_rate": 90,
        "last_10": 9
    },
    {
        "player": "Brock Boeser",
        "team": "VAN",
        "opponent": "EDM",
        "hit_rate": 90,
        "last_10": 9
    },
    {
        "player": "Connor McDavid",
        "team": "EDM",
        "opponent": "VAN",
        "hit_rate": 90,
        "last_10": 9
    },
    {
        "player": "Ryan Winterton",
        "team": "SEA",
        "opponent": "COL",
        "hit_rate": 90,
        "last_10": 9
    },
    {
        "player": "Brandon Montour",
        "team": "SEA",
        "opponent": "COL",
        "hit_rate": 90,
        "last_10": 9
    },
    {
        "player": "Nathan MacKinnon",
        "team": "COL",
        "opponent": "SEA",
        "hit_rate": 90,
        "last_10": 9
    },
    {
        "player": "Martin Necas",
        "team": "COL",
        "opponent": "SEA",
        "hit_rate": 90,
        "last_10": 9
    },
    {
        "player": "Cale Makar",
        "team": "COL",
        "opponent": "SEA",
        "hit_rate": 90,
        "last_10": 9
    },
    {
        "player": "Lawson Crouse",
        "team": "UTA",
        "opponent": "STL",
        "hit_rate": 80,
        "last_10": 8
    },
    {
        "player": "Nick Schmaltz",
        "team": "UTA",
        "opponent": "STL",
        "hit_rate": 80,
        "last_10": 8
    },
    {
        "player": "Leo Carlsson",
        "team": "ANA",
        "opponent": "NSH",
        "hit_rate": 80,
        "last_10": 8
    },
    {
        "player": "Beckett Sennecke",
        "team": "ANA",
        "opponent": "NSH",
        "hit_rate": 80,
        "last_10": 8
    },
    {
        "player": "John Carlson",
        "team": "ANA",
        "opponent": "NSH",
        "hit_rate": 80,
        "last_10": 8
    },
    {
        "player": "Steven Stamkos",
        "team": "NSH",
        "opponent": "ANA",
        "hit_rate": 80,
        "last_10": 8
    },
    {
        "player": "Josh Morrissey",
        "team": "WPG",
        "opponent": "SJS",
        "hit_rate": 80,
        "last_10": 8
    },
    {
        "player": "Joel Armia",
        "team": "LAK",
        "opponent": "CGY",
        "hit_rate": 80,
        "last_10": 8
    },
    {
        "player": "Quinton Byfield",
        "team": "LAK",
        "opponent": "CGY",
        "hit_rate": 80,
        "last_10": 8
    },
    {
        "player": "Jake DeBrusk",
        "team": "VAN",
        "opponent": "EDM",
        "hit_rate": 80,
        "last_10": 8
    },
    {
        "player": "Nazem Kadri",
        "team": "COL",
        "opponent": "SEA",
        "hit_rate": 80,
        "last_10": 8
    },
    {
        "player": "Brent Burns",
        "team": "COL",
        "opponent": "SEA",
        "hit_rate": 80,
        "last_10": 8
    },
    {
        "player": "Sam Malinski",
        "team": "COL",
        "opponent": "SEA",
        "hit_rate": 80,
        "last_10": 8
    }
]