[
    {
        "player": "Cole Smith",
        "team": "VGK",
        "opponent": "COL",
        "hit_rate": 100,
        "last_10": 10
    },
    {
        "player": "Kaedan Korczak",
        "team": "VGK",
        "opponent": "COL",
        "hit_rate": 100,
        "last_10": 10
    },
    {
        "player": "Zakhar Bardakov",
        "team": "COL",
        "opponent": "VGK",
        "hit_rate": 90,
        "last_10": 9
    },
    {
        "player": "Nicolas Roy",
        "team": "COL",
        "opponent": "VGK",
        "hit_rate": 90,
        "last_10": 9
    },
    {
        "player": "Brett Kulak",
        "team": "COL",
        "opponent": "VGK",
        "hit_rate": 90,
        "last_10": 9
    },
    {
        "player": "Nic Dowd",
        "team": "VGK",
        "opponent": "COL",
        "hit_rate": 90,
        "last_10": 9
    },
    {
        "player": "Keegan Kolesar",
        "team": "VGK",
        "opponent": "COL",
        "hit_rate": 90,
        "last_10": 9
    },
    {
        "player": "Colton Sissons",
        "team": "VGK",
        "opponent": "COL",
        "hit_rate": 90,
        "last_10": 9
    },
    {
        "player": "Jack Drury",
        "team": "COL",
        "opponent": "VGK",
        "hit_rate": 80,
        "last_10": 8
    },
    {
        "player": "Joel Kiviranta",
        "team": "COL",
        "opponent": "VGK",
        "hit_rate": 80,
        "last_10": 8
    },
    {
        "player": "Jack Ahcan",
        "team": "COL",
        "opponent": "VGK",
        "hit_rate": 80,
        "last_10": 8
    },
    {
        "player": "Rasmus Andersson",
        "team": "VGK",
        "opponent": "COL",
        "hit_rate": 80,
        "last_10": 8
    },
    {
        "player": "Ben Hutton",
        "team": "VGK",
        "opponent": "COL",
        "hit_rate": 80,
        "last_10": 8
    }
]